aiodine/__init__.py
aiodine/compat.py
aiodine/consumers.py
aiodine/datatypes.py
aiodine/exceptions.py
aiodine/providers.py
aiodine/scopes.py
aiodine/sessions.py
aiodine/store.py
tests/__init__.py
tests/conftest.py
tests/test_async_providers.py
tests/test_autouse.py
tests/test_consumers.py
tests/test_context_providers.py
tests/test_decorators.py
tests/test_discover_default.py
tests/test_discover_modules.py
tests/test_generator_providers.py
tests/test_names.py
tests/test_nested_providers.py
tests/test_override_provider.py
tests/test_provider_factories.py
tests/test_scopes.py
tests/test_sessions.py
tests/test_useprovider.py
aiodine-1.2.9.dist-info/LICENSE
aiodine-1.2.9.dist-info/METADATA
aiodine-1.2.9.dist-info/WHEEL
aiodine-1.2.9.dist-info/top_level.txt
aiodine-1.2.9.dist-info/RECORD
