Metadata-Version: 2.1
Name: aiodine
Version: 1.2.9
Summary: Async-first dependency injection library for Python
Home-page: https://github.com/bocadilloproject/aiodine
Author: Florimond Manca
Author-email: florimond.manca@gmail.com
License: MIT
Platform: UNKNOWN
Classifier: Development Status :: 1 - Planning
Classifier: Intended Audience :: Developers
Classifier: License :: OSI Approved :: MIT License
Classifier: Natural Language :: English
Classifier: Operating System :: OS Independent
Classifier: Programming Language :: Python :: 3 :: Only
Classifier: Programming Language :: Python :: 3.6
Classifier: Programming Language :: Python :: 3.7
Classifier: Framework :: AsyncIO
Classifier: Topic :: Software Development :: Libraries :: Python Modules
Requires-Python: >=3.6
Requires-Dist: async-exit-stack ; python_version < "3.7"
Requires-Dist: aiocontextvars ; python_version < "3.7"
